{
  "pageInfo": {
    "totalPageSize": 5,
    "totalRecSize": 45,
    "page": 1
  },
  "datas": [
    {
      "id": "11111",
      "title": "修改標題1",
      "description": "描述1",
      "url" : "https://www.google.com.tw",
      "picture" : "/resource/6d8955d3-9194-4f3a-870c-6980ad857a91.jpg"
    },
    {
      "id": "11111",
      "title": "修改標題2",
      "description": "描述2",
      "url" : "https://www.google.com.tw",
      "picture" : "/resource/6d8955d3-9194-4f3a-870c-6980ad857a91.jpg"
    }
  ]
}