{
  "pageInfo": {
    "page": 1,
    "totalPageSize": 1,
    "totalRecSize": 1
  },
  "can_create": false,
  "can_checkbox": false,
  "datas": [{
    "data_id": "slider-temp-data-1",
    "is_checked": false,
    "actions": [
      "preview",
      "modify",
      "auditing"
    ],
    "columns": [{
        "display_type": "LABEL",
        "value": "abtesting",
        "display_text": "標題名稱"
      },
      {
        "display_type": "LABEL",
        "value": "a.jpg",
        "display_text": "圖片"
      },
      {
        "display_type": "LABEL",
        "value": "2019-09-22T00:00:00+0800",
        "display_text": "開始時間"
      },
      {
        "display_type": "LABEL",
        "value": "9999-12-31T00:00:00+0800",
        "display_text": "結束時間"
      },
      {
        "display_type": "LABEL",
        "value": "2020-07-14T10:58:49+0800",
        "display_text": "修改時間"
      },
      {
        "display_type": "LABEL",
        "value": "草稿",
        "display_text": "資料狀態"
      }
    ]
  }]
}
